dewdl/__init__.py
dewdl/__main__.py
dewdl/_dewdl_configs.py
dewdl/py.typed
dewdl/_cli/_cli_main.py
dewdl/_cli/_config_interface.py
dewdl/enums/__init__.py
dewdl/enums/_udl_data_mode.py
dewdl/enums/_udl_environment.py
dewdl/enums/_udl_filedrop_type.py
dewdl/enums/_udl_query_type.py
dewdl/enums/_udl_request_error_code.py
dewdl/enums/_udl_request_success_code.py
dewdl/enums/_udl_secure_message_topic.py
dewdl/enums/_udl_secure_message_type.py
dewdl/exceptions/__init__.py
dewdl/exceptions/_udl_request_error.py
dewdl/models/__init__.py
dewdl/models/_elset.py
dewdl/models/_notification.py
dewdl/models/_topic_description.py
dewdl/requests/__init__.py
dewdl/requests/_udl_filedrop.py
dewdl/requests/_udl_query.py
dewdl/requests/_udl_request.py
dewdl/requests/_udl_secure_message.py
dewdl-0.2.4.dist-info/METADATA
dewdl-0.2.4.dist-info/WHEEL
dewdl-0.2.4.dist-info/entry_points.txt
dewdl-0.2.4.dist-info/RECORD
